printsum/__init__.py
printsum/main.py
testpag-0.0.1.dist-info/LICENSE
testpag-0.0.1.dist-info/METADATA
testpag-0.0.1.dist-info/WHEEL
testpag-0.0.1.dist-info/top_level.txt
testpag-0.0.1.dist-info/RECORD
