Metadata-Version: 2.1
Name: testpag
Version: 0.0.1
Summary: Some description
Home-page: https://github.com/friedwok
Author: Pavel P.
Author-email: pasha228@gmail.com
License: UNKNOWN
Platform: UNKNOWN
Classifier: Programming Language :: Python :: 3.8
Classifier: License :: OSI Approved :: MIT License
Classifier: Operating System :: OS Independent
Requires-Python: >=3.6
